README.rst
setup.cfg
setup.py
aibuildersart/__init__.py
aibuildersart/asciiart.py
aibuildersart.egg-info/PKG-INFO
aibuildersart.egg-info/SOURCES.txt
aibuildersart.egg-info/dependency_links.txt
aibuildersart.egg-info/top_level.txt