Metadata-Version: 1.1
Name: aibuildersart
Version: 0.0.1
Summary: ASCII ART by AIBuilders member
Home-page: https://github.com/UncleEngineer/AIBuildersArt
Author: AIBuilders member
Author-email: loong.wissawakorn@gmail.com
License: MIT
Download-URL: https://github.com/UncleEngineer/AIBuildersArt/archive/v0.0.1.zip
Keywords: ASCII,AIBuilders,Uncle Engineer
Platform: UNKNOWN
Classifier: Development Status :: 3 - Alpha
Classifier: Intended Audience :: Education
Classifier: Topic :: Software Development :: Build Tools
Classifier: License :: OSI Approved :: MIT License
Classifier: Programming Language :: Python :: 3
Classifier: Programming Language :: Python :: 3.4
Classifier: Programming Language :: Python :: 3.5
Classifier: Programming Language :: Python :: 3.6
Classifier: Programming Language :: Python :: 3.7
Classifier: Programming Language :: Python :: 3.8
Classifier: Programming Language :: Python :: 3.9
